depth_tools/__init__.py
depth_tools/_align_depth_univ.py
depth_tools/_camera.py
depth_tools/_coord_sys.py
depth_tools/_datasets.py
depth_tools/_depth_clip.py
depth_tools/_depth_map_dilation.py
depth_tools/_dist_maps_univ.py
depth_tools/_diverging_functions_internal.py
depth_tools/_format_checks_internal.py
depth_tools/_logging_internal.py
depth_tools/_losses_univ.py
depth_tools/_normalize_values_univ.py
depth_tools/_nyuv2_util_internal.py
depth_tools/_object_insertion.py
depth_tools/_point_cloud.py
depth_tools/_vec_len_map_internal.py
depth_tools/hypersim_metadata_original/camera_parameters.csv
depth_tools/hypersim_metadata_original/issue_22_rejections.txt
depth_tools/hypersim_metadata_original/metadata_images_split_scene_v1.csv
depth_tools/hypersim_splits/test.txt
depth_tools/hypersim_splits/toy.txt
depth_tools/hypersim_splits/train.txt
depth_tools/hypersim_splits/val.txt
depth_tools/pt/__init__.py
depth_tools/pt/_align_depth_univ.py
depth_tools/pt/_datasets.py
depth_tools/pt/_depth_clip.py
depth_tools/pt/_depth_map_dilation.py
depth_tools/pt/_dist_maps_univ.py
depth_tools/pt/_diverging_functions_internal.py
depth_tools/pt/_format_checks_internal.py
depth_tools/pt/_losses_univ.py
depth_tools/pt/_normalize_values_univ.py
depth_tools/pt/_vec_len_map_internal.py
depth_tools-0.5.0.dist-info/METADATA
depth_tools-0.5.0.dist-info/WHEEL
depth_tools-0.5.0.dist-info/top_level.txt
depth_tools-0.5.0.dist-info/RECORD
