Metadata-Version: 2.4
Name: depth_tools
Version: 0.5.0
Summary: A simple pure Python implementation of depth-related calculations.
License: MIT License
Project-URL: Homepage, https://github.com/mntusr/depth_tools
Classifier: Development Status :: 4 - Beta
Classifier: License :: OSI Approved :: MIT License
Classifier: Programming Language :: Python
Requires-Python: >=3.10
Requires-Dist: numpy>=1.24.0
Requires-Dist: typing-extensions>=4.0.0
Provides-Extra: datasets
Requires-Dist: scipy>=1.9.0; extra == "datasets"
Requires-Dist: h5py>=3.7.0; extra == "datasets"
Requires-Dist: Pillow>=9.3.0; extra == "datasets"
Requires-Dist: pandas>=1.5.0; extra == "datasets"
Provides-Extra: plots
Requires-Dist: matplotlib>=3.6.0; extra == "plots"
Requires-Dist: plotly>=5.13.0; extra == "plots"
